aiotplink/__init__.py
aiotplink/__main__.py
aiotplink/commands.py
aiotplink/devices.py
aiotplink/discover.py
aiotplink-0.1.0b1.dist-info/DESCRIPTION.rst
aiotplink-0.1.0b1.dist-info/METADATA
aiotplink-0.1.0b1.dist-info/RECORD
aiotplink-0.1.0b1.dist-info/WHEEL
aiotplink-0.1.0b1.dist-info/metadata.json
aiotplink-0.1.0b1.dist-info/top_level.txt
