Metadata-Version: 2.0
Name: aiotplink
Version: 0.1.0b1
Summary: API for local communication with TP-Link Smart Plugs devices over a LAN with asyncio.
Home-page: http://github.com/frawau/aiotplink
Author: François Wautier
Author-email: francois@wautier.eu
License: MIT
Download-URL: https://github.com/frawau/aiotplink/archive/0.1.0b1.tar.gz
Keywords: TP-Link,IoT,switch,Smart Plug,automation
Platform: UNKNOWN
Classifier: License :: OSI Approved :: MIT License
Classifier: Programming Language :: Python :: 3
Classifier: Programming Language :: Python :: 3.5
